pyplot_cli/__init__.py
pyplot_cli/cli.py
pyplot_cli/io.py
pyplot_cli-0.1.0.dist-info/entry_points.txt
pyplot_cli-0.1.0.dist-info/WHEEL
pyplot_cli-0.1.0.dist-info/METADATA
pyplot_cli-0.1.0.dist-info/RECORD
